{"dapper":{"status":"OK","dappName":"HNhomepage","applyToUrl":"http:\/\/news.ycombinator.com\/","executionTime":"0.245","ranAt":"2012-10-02 22:35:02 UTC","inputVars":""},"groups":{"Post":[{"Title":[{"value":"The $1 billion mission to reach the Earth's mantle","href":"http:\/\/edition.cnn.com\/2012\/10\/01\/tech\/mantle-earth-drill-mission\/index.html?c=&page=1","originalElement":"a","fieldName":"Title"}],"Domain":[{"value":"(cnn.com)","originalElement":"span","fieldName":"Domain"}],"PointsNum":[{"value":"88 points","originalElement":"span","fieldName":"PointsNum"}],"SubmittedBy":[{"value":"ssclafani","href":"http:\/\/news.ycombinator.com\/user?id=ssclafani","originalElement":"a","fieldName":"SubmittedBy"}],"WhenPosted":[{"value":"2 hours ago |","originalElement":"span","fieldName":"WhenPosted"}],"NumComments":[{"value":"28 comments","href":"http:\/\/news.ycombinator.com\/item?id=4603847","originalElement":"a","fieldName":"NumComments"}]},{"Title":[{"value":"Show HN: I built a stock market game based on the top 50,000 websites","href":"http:\/\/linkdaq.net","originalElement":"a","fieldName":"Title"}],"Domain":[{"value":"(linkdaq.net)","originalElement":"span","fieldName":"Domain"}],"PointsNum":[{"value":"45 points","originalElement":"span","fieldName":"PointsNum"}],"SubmittedBy":[{"value":"thehodge","href":"http:\/\/news.ycombinator.com\/user?id=thehodge","originalElement":"a","fieldName":"SubmittedBy"}],"WhenPosted":[{"value":"2 hours ago |","originalElement":"span","fieldName":"WhenPosted"}],"NumComments":[{"value":"23 comments","href":"http:\/\/news.ycombinator.com\/item?id=4604099","originalElement":"a","fieldName":"NumComments"}]},{"Title":[{"value":"Software on Steam","href":"http:\/\/store.steampowered.com\/software","originalElement":"a","fieldName":"Title"}],"Domain":[{"value":"(steampowered.com)","originalElement":"span","fieldName":"Domain"}],"PointsNum":[{"value":"127 points","originalElement":"span","fieldName":"PointsNum"}],"SubmittedBy":[{"value":"mxfh","href":"http:\/\/news.ycombinator.com\/user?id=mxfh","originalElement":"a","fieldName":"SubmittedBy"}],"WhenPosted":[{"value":"4 hours ago |","originalElement":"span","fieldName":"WhenPosted"}],"NumComments":[{"value":"65 comments","href":"http:\/\/news.ycombinator.com\/item?id=4603316","originalElement":"a","fieldName":"NumComments"}]},{"Title":[{"value":"Lockitron: Keyless entry using your phone","href":"https:\/\/lockitron.com\/preorder","originalElement":"a","fieldName":"Title"}],"Domain":[{"value":"(lockitron.com)","originalElement":"span","fieldName":"Domain"}],"PointsNum":[{"value":"218 points","originalElement":"span","fieldName":"PointsNum"}],"SubmittedBy":[{"value":"tylerhowarth","href":"http:\/\/news.ycombinator.com\/user?id=tylerhowarth","originalElement":"a","fieldName":"SubmittedBy"}],"WhenPosted":[{"value":"6 hours ago |","originalElement":"span","fieldName":"WhenPosted"}],"NumComments":[{"value":"147 comments","href":"http:\/\/news.ycombinator.com\/item?id=4602679","originalElement":"a","fieldName":"NumComments"}]},{"Title":[{"value":"The Sudden, Mysterious Exit Of A Quora Cofounder Has Silicon Valley Baffled","href":"http:\/\/www.sfgate.com\/technology\/businessinsider\/article\/The-Sudden-Mysterious-Exit-Of-A-Quora-Cofounder-3912160.php","originalElement":"a","fieldName":"Title"}],"Domain":[{"value":"(sfgate.com)","originalElement":"span","fieldName":"Domain"}],"PointsNum":[{"value":"198 points","originalElement":"span","fieldName":"PointsNum"}],"SubmittedBy":[{"value":"steve8918","href":"http:\/\/news.ycombinator.com\/user?id=steve8918","originalElement":"a","fieldName":"SubmittedBy"}],"WhenPosted":[{"value":"7 hours ago |","originalElement":"span","fieldName":"WhenPosted"}],"NumComments":[{"value":"96 comments","href":"http:\/\/news.ycombinator.com\/item?id=4602436","originalElement":"a","fieldName":"NumComments"}]},{"Title":[{"value":"Drupal's Golden Handcuffs","href":"http:\/\/mikecr.it\/ramblings\/drupals-golden-handcuffs","originalElement":"a","fieldName":"Title"}],"Domain":[{"value":"(mikecr.it)","originalElement":"span","fieldName":"Domain"}],"PointsNum":[{"value":"14 points","originalElement":"span","fieldName":"PointsNum"}],"SubmittedBy":[{"value":"mcrittenden","href":"http:\/\/news.ycombinator.com\/user?id=mcrittenden","originalElement":"a","fieldName":"SubmittedBy"}],"WhenPosted":[{"value":"46 minutes ago |","originalElement":"span","fieldName":"WhenPosted"}],"NumComments":[{"value":"3 comments","href":"http:\/\/news.ycombinator.com\/item?id=4604555","originalElement":"a","fieldName":"NumComments"}]},{"Title":[{"value":"Keccak wins the SHA-3 competition","href":"http:\/\/csrc.nist.gov\/groups\/ST\/hash\/sha-3\/winner_sha-3.html","originalElement":"a","fieldName":"Title"}],"Domain":[{"value":"(nist.gov)","originalElement":"span","fieldName":"Domain"}],"PointsNum":[{"value":"10 points","originalElement":"span","fieldName":"PointsNum"}],"SubmittedBy":[{"value":"B-Con","href":"http:\/\/news.ycombinator.com\/user?id=B-Con","originalElement":"a","fieldName":"SubmittedBy"}],"WhenPosted":[{"value":"25 minutes ago |","originalElement":"span","fieldName":"WhenPosted"}],"NumComments":[{"value":"1 comment","href":"http:\/\/news.ycombinator.com\/item?id=4604646","originalElement":"a","fieldName":"NumComments"}]},{"Title":[{"value":"Lenovo Computers, Soon To Be Made In America","href":"http:\/\/techcrunch.com\/2012\/10\/02\/lenovo-computers-soon-to-be-made-in-america\/","originalElement":"a","fieldName":"Title"}],"Domain":[{"value":"(techcrunch.com)","originalElement":"span","fieldName":"Domain"}],"PointsNum":[{"value":"63 points","originalElement":"span","fieldName":"PointsNum"}],"SubmittedBy":[{"value":"andreiursan","href":"http:\/\/news.ycombinator.com\/user?id=andreiursan","originalElement":"a","fieldName":"SubmittedBy"}],"WhenPosted":[{"value":"3 hours ago |","originalElement":"span","fieldName":"WhenPosted"}],"NumComments":[{"value":"39 comments","href":"http:\/\/news.ycombinator.com\/item?id=4603529","originalElement":"a","fieldName":"NumComments"}]},{"Title":[{"value":"The Story of the New Microsoft.com","href":"http:\/\/rainypixels.com\/words\/the-story-of-the-new-microsoft-com\/","originalElement":"a","fieldName":"Title"}],"Domain":[{"value":"(rainypixels.com)","originalElement":"span","fieldName":"Domain"}],"PointsNum":[{"value":"126 points","originalElement":"span","fieldName":"PointsNum"}],"SubmittedBy":[{"value":"robin_reala","href":"http:\/\/news.ycombinator.com\/user?id=robin_reala","originalElement":"a","fieldName":"SubmittedBy"}],"WhenPosted":[{"value":"6 hours ago |","originalElement":"span","fieldName":"WhenPosted"}],"NumComments":[{"value":"49 comments","href":"http:\/\/news.ycombinator.com\/item?id=4602638","originalElement":"a","fieldName":"NumComments"}]},{"Title":[{"value":"Discovery Channel's Inside a Jet Crash","href":"http:\/\/www.usatoday.com\/story\/travel\/flights\/2012\/10\/01\/inside-a-doomed-jetliner-tv-show-stages-727-crash\/1606749\/","originalElement":"a","fieldName":"Title"}],"Domain":[{"value":"(usatoday.com)","originalElement":"span","fieldName":"Domain"}],"PointsNum":[{"value":"24 points","originalElement":"span","fieldName":"PointsNum"}],"SubmittedBy":[{"value":"twakefield","href":"http:\/\/news.ycombinator.com\/user?id=twakefield","originalElement":"a","fieldName":"SubmittedBy"}],"WhenPosted":[{"value":"2 hours ago |","originalElement":"span","fieldName":"WhenPosted"}],"NumComments":[{"value":"6 comments","href":"http:\/\/news.ycombinator.com\/item?id=4604089","originalElement":"a","fieldName":"NumComments"}]},{"Title":[{"value":"How We Doubled Our Android Install Rate in One Hour","href":"http:\/\/www.dwellable.com\/blog\/How-We-Doubled-Our-Android-Install-Rate-in-One-Hour","originalElement":"a","fieldName":"Title"}],"Domain":[{"value":"(dwellable.com)","originalElement":"span","fieldName":"Domain"}],"PointsNum":[{"value":"68 points","originalElement":"span","fieldName":"PointsNum"}],"SubmittedBy":[{"value":"gurgeous","href":"http:\/\/news.ycombinator.com\/user?id=gurgeous","originalElement":"a","fieldName":"SubmittedBy"}],"WhenPosted":[{"value":"4 hours ago |","originalElement":"span","fieldName":"WhenPosted"}],"NumComments":[{"value":"17 comments","href":"http:\/\/news.ycombinator.com\/item?id=4603188","originalElement":"a","fieldName":"NumComments"}]},{"Title":[{"value":"Social Login Buttons Aren\u2019t Worth It","href":"https:\/\/blog.mailchimp.com\/social-login-buttons-arent-worth-it\/","originalElement":"a","fieldName":"Title"}],"Domain":[{"value":"(mailchimp.com)","originalElement":"span","fieldName":"Domain"}],"PointsNum":[{"value":"67 points","originalElement":"span","fieldName":"PointsNum"}],"SubmittedBy":[{"value":"ryanfitz","href":"http:\/\/news.ycombinator.com\/user?id=ryanfitz","originalElement":"a","fieldName":"SubmittedBy"}],"WhenPosted":[{"value":"4 hours ago |","originalElement":"span","fieldName":"WhenPosted"}],"NumComments":[{"value":"35 comments","href":"http:\/\/news.ycombinator.com\/item?id=4603204","originalElement":"a","fieldName":"NumComments"}]},{"Title":[{"value":"Understanding Postgres Performance","href":"http:\/\/craigkerstiens.com\/2012\/10\/01\/understanding-postgres-performance\/","originalElement":"a","fieldName":"Title"}],"Domain":[{"value":"(craigkerstiens.com)","originalElement":"span","fieldName":"Domain"}],"PointsNum":[{"value":"124 points","originalElement":"span","fieldName":"PointsNum"}],"SubmittedBy":[{"value":"neilmiddleton","href":"http:\/\/news.ycombinator.com\/user?id=neilmiddleton","originalElement":"a","fieldName":"SubmittedBy"}],"WhenPosted":[{"value":"7 hours ago |","originalElement":"span","fieldName":"WhenPosted"}],"NumComments":[{"value":"28 comments","href":"http:\/\/news.ycombinator.com\/item?id=4602275","originalElement":"a","fieldName":"NumComments"}]},{"Title":[{"value":"Online Python Tutor: Learn programming by visualizing code execution","href":"http:\/\/pythontutor.com\/","originalElement":"a","fieldName":"Title"}],"Domain":[{"value":"(pythontutor.com)","originalElement":"span","fieldName":"Domain"}],"PointsNum":[{"value":"246 points","originalElement":"span","fieldName":"PointsNum"}],"SubmittedBy":[{"value":"ColinWright","href":"http:\/\/news.ycombinator.com\/user?id=ColinWright","originalElement":"a","fieldName":"SubmittedBy"}],"WhenPosted":[{"value":"11 hours ago |","originalElement":"span","fieldName":"WhenPosted"}],"NumComments":[{"value":"34 comments","href":"http:\/\/news.ycombinator.com\/item?id=4601478","originalElement":"a","fieldName":"NumComments"}]},{"Title":[{"value":"The Spy Who Lived it Up","href":"http:\/\/www.nytimes.com\/2012\/09\/23\/us\/edwin-p-wilson-cia-operative-with-cloak-and-dagger-life-dies-at-84.html?smid=fb-share","originalElement":"a","fieldName":"Title"}],"Domain":[{"value":"(nytimes.com)","originalElement":"span","fieldName":"Domain"}],"PointsNum":[{"value":"11 points","originalElement":"span","fieldName":"PointsNum"}],"SubmittedBy":[{"value":"jmspring","href":"http:\/\/news.ycombinator.com\/user?id=jmspring","originalElement":"a","fieldName":"SubmittedBy"}],"WhenPosted":[{"value":"1 hour ago |","originalElement":"span","fieldName":"WhenPosted"}],"NumComments":[{"value":"discuss","href":"http:\/\/news.ycombinator.com\/item?id=4604346","originalElement":"a","fieldName":"NumComments"}]},{"Title":[{"value":"Filepicker.io launches Alfresco, WebDAV, & FTP integrations","href":"https:\/\/www.filepicker.io\/products\/services\/","originalElement":"a","fieldName":"Title"}],"Domain":[{"value":"(filepicker.io)","originalElement":"span","fieldName":"Domain"}],"PointsNum":[{"value":"5 points","originalElement":"span","fieldName":"PointsNum"}],"SubmittedBy":[{"value":"ananddass","href":"http:\/\/news.ycombinator.com\/user?id=ananddass","originalElement":"a","fieldName":"SubmittedBy"}],"WhenPosted":[{"value":"18 minutes ago |","originalElement":"span","fieldName":"WhenPosted"}],"NumComments":[{"value":"5 comments","href":"http:\/\/news.ycombinator.com\/item?id=4604673","originalElement":"a","fieldName":"NumComments"}]},{"Title":[{"value":"Racism at a gaming company","href":"http:\/\/qu33riousity.tumblr.com\/post\/32659337104\/racist-moments-of-2012-pt-1-the-workplace","originalElement":"a","fieldName":"Title"}],"Domain":[{"value":"(qu33riousity.tumblr.com)","originalElement":"span","fieldName":"Domain"}],"PointsNum":[{"value":"257 points","originalElement":"span","fieldName":"PointsNum"}],"SubmittedBy":[{"value":"plinkplonk","href":"http:\/\/news.ycombinator.com\/user?id=plinkplonk","originalElement":"a","fieldName":"SubmittedBy"}],"WhenPosted":[{"value":"3 hours ago |","originalElement":"span","fieldName":"WhenPosted"}],"NumComments":[{"value":"285 comments","href":"http:\/\/news.ycombinator.com\/item?id=4603611","originalElement":"a","fieldName":"NumComments"}]},{"Title":[{"value":"Show HN: Meet your cardboard buddy.","href":"http:\/\/foldable.me","originalElement":"a","fieldName":"Title"}],"Domain":[{"value":"(foldable.me)","originalElement":"span","fieldName":"Domain"}],"PointsNum":[{"value":"214 points","originalElement":"span","fieldName":"PointsNum"}],"SubmittedBy":[{"value":"hakkasan","href":"http:\/\/news.ycombinator.com\/user?id=hakkasan","originalElement":"a","fieldName":"SubmittedBy"}],"WhenPosted":[{"value":"11 hours ago |","originalElement":"span","fieldName":"WhenPosted"}],"NumComments":[{"value":"95 comments","href":"http:\/\/news.ycombinator.com\/item?id=4601366","originalElement":"a","fieldName":"NumComments"}]},{"Title":[{"value":"Meet the 2012 MacArthur Fellows","href":"http:\/\/www.macfound.org\/fellows\/class\/2012\/","originalElement":"a","fieldName":"Title"}],"Domain":[{"value":"(macfound.org)","originalElement":"span","fieldName":"Domain"}],"PointsNum":[{"value":"19 points","originalElement":"span","fieldName":"PointsNum"}],"SubmittedBy":[{"value":"clbrook","href":"http:\/\/news.ycombinator.com\/user?id=clbrook","originalElement":"a","fieldName":"SubmittedBy"}],"WhenPosted":[{"value":"2 hours ago |","originalElement":"span","fieldName":"WhenPosted"}],"NumComments":[{"value":"7 comments","href":"http:\/\/news.ycombinator.com\/item?id=4603809","originalElement":"a","fieldName":"NumComments"}]},{"Title":[{"value":"20,000 users in a week - Jetstrap HN Front Page Stats","href":"http:\/\/blog.jetstrap.com\/2012\/10\/20000-users-in-a-week-hn-front-page-post-mortem\/","originalElement":"a","fieldName":"Title"}],"Domain":[{"value":"(jetstrap.com)","originalElement":"span","fieldName":"Domain"}],"PointsNum":[{"value":"28 points","originalElement":"span","fieldName":"PointsNum"}],"SubmittedBy":[{"value":"yesimahuman","href":"http:\/\/news.ycombinator.com\/user?id=yesimahuman","originalElement":"a","fieldName":"SubmittedBy"}],"WhenPosted":[{"value":"4 hours ago |","originalElement":"span","fieldName":"WhenPosted"}],"NumComments":[{"value":"6 comments","href":"http:\/\/news.ycombinator.com\/item?id=4603429","originalElement":"a","fieldName":"NumComments"}]},{"Title":[{"value":"Google Maps heatmap of GitHub repository stargazers","href":"https:\/\/github.com\/rviscomi\/red-dwarf","originalElement":"a","fieldName":"Title"}],"Domain":[{"value":"(github.com)","originalElement":"span","fieldName":"Domain"}],"PointsNum":[{"value":"17 points","originalElement":"span","fieldName":"PointsNum"}],"SubmittedBy":[{"value":"lest","href":"http:\/\/news.ycombinator.com\/user?id=lest","originalElement":"a","fieldName":"SubmittedBy"}],"WhenPosted":[{"value":"3 hours ago |","originalElement":"span","fieldName":"WhenPosted"}],"NumComments":[{"value":"7 comments","href":"http:\/\/news.ycombinator.com\/item?id=4603756","originalElement":"a","fieldName":"NumComments"}]},{"Title":[{"value":"How to Model Viral Growth: The Hybrid Model","href":"http:\/\/www.linkedin.com\/today\/post\/article\/20121002124206-18876785-how-to-model-viral-growth-the-hybrid-model","originalElement":"a","fieldName":"Title"}],"Domain":[{"value":"(linkedin.com)","originalElement":"span","fieldName":"Domain"}],"PointsNum":[{"value":"32 points","originalElement":"span","fieldName":"PointsNum"}],"SubmittedBy":[{"value":"nikunjk","href":"http:\/\/news.ycombinator.com\/user?id=nikunjk","originalElement":"a","fieldName":"SubmittedBy"}],"WhenPosted":[{"value":"4 hours ago |","originalElement":"span","fieldName":"WhenPosted"}],"NumComments":[{"value":"5 comments","href":"http:\/\/news.ycombinator.com\/item?id=4603202","originalElement":"a","fieldName":"NumComments"}]},{"Title":[{"value":"How To Build A Blog Readership","href":"http:\/\/danshipper.com\/how-to-build-a-blog-readership#","originalElement":"a","fieldName":"Title"}],"Domain":[{"value":"(danshipper.com)","originalElement":"span","fieldName":"Domain"}],"PointsNum":[{"value":"84 points","originalElement":"span","fieldName":"PointsNum"}],"SubmittedBy":[{"value":"dshipper","href":"http:\/\/news.ycombinator.com\/user?id=dshipper","originalElement":"a","fieldName":"SubmittedBy"}],"WhenPosted":[{"value":"8 hours ago |","originalElement":"span","fieldName":"WhenPosted"}],"NumComments":[{"value":"27 comments","href":"http:\/\/news.ycombinator.com\/item?id=4602046","originalElement":"a","fieldName":"NumComments"}]},{"Title":[{"value":"Leak of Multiple University Databases","href":"http:\/\/pastebin.com\/AQWhu8Ek","originalElement":"a","fieldName":"Title"}],"Domain":[{"value":"(pastebin.com)","originalElement":"span","fieldName":"Domain"}],"PointsNum":[{"value":"33 points","originalElement":"span","fieldName":"PointsNum"}],"SubmittedBy":[{"value":"jmediast","href":"http:\/\/news.ycombinator.com\/user?id=jmediast","originalElement":"a","fieldName":"SubmittedBy"}],"WhenPosted":[{"value":"3 hours ago |","originalElement":"span","fieldName":"WhenPosted"}],"NumComments":[{"value":"11 comments","href":"http:\/\/news.ycombinator.com\/item?id=4603558","originalElement":"a","fieldName":"NumComments"}]},{"Title":[{"value":"Show HN: Summaries of interesting content, written by people","href":"http:\/\/tldr.io","originalElement":"a","fieldName":"Title"}],"Domain":[{"value":"(tldr.io)","originalElement":"span","fieldName":"Domain"}],"PointsNum":[{"value":"84 points","originalElement":"span","fieldName":"PointsNum"}],"SubmittedBy":[{"value":"louischatriot","href":"http:\/\/news.ycombinator.com\/user?id=louischatriot","originalElement":"a","fieldName":"SubmittedBy"}],"WhenPosted":[{"value":"7 hours ago |","originalElement":"span","fieldName":"WhenPosted"}],"NumComments":[{"value":"76 comments","href":"http:\/\/news.ycombinator.com\/item?id=4602377","originalElement":"a","fieldName":"NumComments"}]},{"Title":[{"value":"Justice Department to defend warrantless cell phone tracking","href":"http:\/\/news.cnet.com\/8301-13578_3-57524109-38\/justice-dept-to-defend-warrantless-cell-phone-tracking\/","originalElement":"a","fieldName":"Title"}],"Domain":[{"value":"(cnet.com)","originalElement":"span","fieldName":"Domain"}],"PointsNum":[{"value":"35 points","originalElement":"span","fieldName":"PointsNum"}],"SubmittedBy":[{"value":"dhconnelly","href":"http:\/\/news.ycombinator.com\/user?id=dhconnelly","originalElement":"a","fieldName":"SubmittedBy"}],"WhenPosted":[{"value":"5 hours ago |","originalElement":"span","fieldName":"WhenPosted"}],"NumComments":[{"value":"14 comments","href":"http:\/\/news.ycombinator.com\/item?id=4602966","originalElement":"a","fieldName":"NumComments"}]},{"Title":[{"value":"Zenbox Omniwrite: Powerful customer admin panel works with your existing SaaS","href":"http:\/\/blog.zenboxapp.com\/zenbox-omniwrite-a-supercharged-customer-admi","originalElement":"a","fieldName":"Title"}],"Domain":[{"value":"(zenboxapp.com)","originalElement":"span","fieldName":"Domain"}],"PointsNum":[{"value":"32 points","originalElement":"span","fieldName":"PointsNum"}],"SubmittedBy":[{"value":"sgrove","href":"http:\/\/news.ycombinator.com\/user?id=sgrove","originalElement":"a","fieldName":"SubmittedBy"}],"WhenPosted":[{"value":"5 hours ago |","originalElement":"span","fieldName":"WhenPosted"}],"NumComments":[{"value":"6 comments","href":"http:\/\/news.ycombinator.com\/item?id=4602944","originalElement":"a","fieldName":"NumComments"}]},{"Title":[{"value":"Why does TypeScript have be the answer to anything?","href":"http:\/\/www.hanselman.com\/blog\/WhyDoesTypeScriptHaveBeTheAnswerToAnything.aspx","originalElement":"a","fieldName":"Title"}],"Domain":[{"value":"(hanselman.com)","originalElement":"span","fieldName":"Domain"}],"PointsNum":[{"value":"81 points","originalElement":"span","fieldName":"PointsNum"}],"SubmittedBy":[{"value":"andrijac","href":"http:\/\/news.ycombinator.com\/user?id=andrijac","originalElement":"a","fieldName":"SubmittedBy"}],"WhenPosted":[{"value":"9 hours ago |","originalElement":"span","fieldName":"WhenPosted"}],"NumComments":[{"value":"57 comments","href":"http:\/\/news.ycombinator.com\/item?id=4601654","originalElement":"a","fieldName":"NumComments"}]},{"Title":[{"value":"Microsoft has their own Windows Phone in the works","href":"http:\/\/www.wpcentral.com\/microsoft-does-indeed-have-their-own-windows-phone","originalElement":"a","fieldName":"Title"}],"Domain":[{"value":"(wpcentral.com)","originalElement":"span","fieldName":"Domain"}],"PointsNum":[{"value":"48 points","originalElement":"span","fieldName":"PointsNum"}],"SubmittedBy":[{"value":"jbillmann","href":"http:\/\/news.ycombinator.com\/user?id=jbillmann","originalElement":"a","fieldName":"SubmittedBy"}],"WhenPosted":[{"value":"5 hours ago |","originalElement":"span","fieldName":"WhenPosted"}],"NumComments":[{"value":"48 comments","href":"http:\/\/news.ycombinator.com\/item?id=4603035","originalElement":"a","fieldName":"NumComments"}]},{"Title":[{"value":"You are getting sleeeeeeepy ...","href":"http:\/\/blogs.discovermagazine.com\/cosmicvariance\/2012\/10\/01\/you-are-getting-sleeeeeeepy\/","originalElement":"a","fieldName":"Title"}],"Domain":[{"value":"(discovermagazine.com)","originalElement":"span","fieldName":"Domain"}],"PointsNum":[{"value":"182 points","originalElement":"span","fieldName":"PointsNum"}],"SubmittedBy":[{"value":"ColinWright","href":"http:\/\/news.ycombinator.com\/user?id=ColinWright","originalElement":"a","fieldName":"SubmittedBy"}],"WhenPosted":[{"value":"15 hours ago |","originalElement":"span","fieldName":"WhenPosted"}],"NumComments":[{"value":"36 comments","href":"http:\/\/news.ycombinator.com\/item?id=4600897","originalElement":"a","fieldName":"NumComments"}]},{"Title":[{"value":"More","href":"http:\/\/news.ycombinator.com\/news2","originalElement":"a","fieldName":"Title"}]}]}}